<?xml version="1.0" encoding="utf-8"?>
<odoo>

    <menuitem
        parent="account.menu_finance_reports"
        id="menu_oca_reports"
        name="OCA accounting reports"
        groups="account.group_account_manager,account.group_account_user"
        />

    <menuitem
        parent="menu_oca_reports"
        action="action_general_ledger_wizard"
        id="menu_general_ledger_wizard"
        sequence="10"
        />

    <menuitem
        parent="menu_oca_reports"
        action="action_trial_balance_wizard"
        id="menu_trial_balance_wizard"
        sequence="20"
        />

    <menuitem
        parent="menu_oca_reports"
        action="action_open_items_wizard"
        id="menu_open_items_wizard"
        sequence="30"
        />

    <menuitem
        parent="menu_oca_reports"
        action="action_aged_partner_balance_wizard"
        id="menu_aged_partner_balance_wizard"
        sequence="40"
        />

    <!-- Hide odoo PDF reports menu -->
    <record id="account.menu_general_ledger" model="ir.ui.menu">
        <field name="groups_id" eval="[(6, 0, [ref('base.group_erp_manager')])]"/>
    </record>

    <record id="account.menu_general_Balance_report" model="ir.ui.menu">
        <field name="groups_id" eval="[(6, 0, [ref('base.group_erp_manager')])]"/>
    </record>

    <record id="account.menu_account_report_bs" model="ir.ui.menu">
        <field name="groups_id" eval="[(6, 0, [ref('base.group_erp_manager')])]"/>
    </record>

    <record id="account.menu_account_report_pl" model="ir.ui.menu">
        <field name="groups_id" eval="[(6, 0, [ref('base.group_erp_manager')])]"/>
    </record>

    <record id="account.menu_aged_trial_balance" model="ir.ui.menu">
        <field name="groups_id" eval="[(6, 0, [ref('base.group_erp_manager')])]"/>
    </record>

</odoo>
